bin/rst2html.py
bin/rst2html5.py
bin/rst2latex.py
bin/rst2man.py
bin/rst2odt.py
bin/rst2odt_prepstyles.py
bin/rst2pseudoxml.py
bin/rst2s5.py
bin/rst2xetex.py
bin/rst2xml.py
bin/rstpep2html.py
build/lib/bin/rst2html.py
build/lib/bin/rst2html5.py
build/lib/bin/rst2latex.py
build/lib/bin/rst2man.py
build/lib/bin/rst2odt.py
build/lib/bin/rst2odt_prepstyles.py
build/lib/bin/rst2pseudoxml.py
build/lib/bin/rst2s5.py
build/lib/bin/rst2xetex.py
build/lib/bin/rst2xml.py
build/lib/bin/rstpep2html.py
build/lib/build/lib/bin/rst2html.py
build/lib/build/lib/bin/rst2html5.py
build/lib/build/lib/bin/rst2latex.py
build/lib/build/lib/bin/rst2man.py
build/lib/build/lib/bin/rst2odt.py
build/lib/build/lib/bin/rst2odt_prepstyles.py
build/lib/build/lib/bin/rst2pseudoxml.py
build/lib/build/lib/bin/rst2s5.py
build/lib/build/lib/bin/rst2xetex.py
build/lib/build/lib/bin/rst2xml.py
build/lib/build/lib/bin/rstpep2html.py
build/lib/build/lib/build/lib/bin/rst2html.py
build/lib/build/lib/build/lib/bin/rst2html5.py
build/lib/build/lib/build/lib/bin/rst2latex.py
build/lib/build/lib/build/lib/bin/rst2man.py
build/lib/build/lib/build/lib/bin/rst2odt.py
build/lib/build/lib/build/lib/bin/rst2odt_prepstyles.py
build/lib/build/lib/build/lib/bin/rst2pseudoxml.py
build/lib/build/lib/build/lib/bin/rst2s5.py
build/lib/build/lib/build/lib/bin/rst2xetex.py
build/lib/build/lib/build/lib/bin/rst2xml.py
build/lib/build/lib/build/lib/bin/rstpep2html.py
build/lib/build/lib/build/lib/build/lib/bin/rst2html.py
build/lib/build/lib/build/lib/build/lib/bin/rst2html5.py
build/lib/build/lib/build/lib/build/lib/bin/rst2latex.py
build/lib/build/lib/build/lib/build/lib/bin/rst2man.py
build/lib/build/lib/build/lib/build/lib/bin/rst2odt.py
build/lib/build/lib/build/lib/build/lib/bin/rst2odt_prepstyles.py
build/lib/build/lib/build/lib/build/lib/bin/rst2pseudoxml.py
build/lib/build/lib/build/lib/build/lib/bin/rst2s5.py
build/lib/build/lib/build/lib/build/lib/bin/rst2xetex.py
xdmenu-1.0.0.dist-info/DESCRIPTION.rst
xdmenu-1.0.0.dist-info/METADATA
xdmenu-1.0.0.dist-info/RECORD
xdmenu-1.0.0.dist-info/WHEEL
xdmenu-1.0.0.dist-info/entry_points.txt
xdmenu-1.0.0.dist-info/metadata.json
xdmenu-1.0.0.dist-info/top_level.txt
