Metadata-Version: 2.0
Name: xdmenu
Version: 1.0.0
Summary: Extensible wrapper for dmenu.
Home-page: https://github.com/cblegare/xdmenu
Author: Charles Bouchard-Légaré
Author-email: cblegare.atl@ntis.ca
License: GNU Lesser General Public License v3
Platform: UNKNOWN
Classifier: Development Status :: 4 - Beta
Classifier: Environment :: Console
Classifier: Environment :: X11 Applications
Classifier: Intended Audience :: Developers
Classifier: License :: OSI Approved :: GNU Lesser General Public License v3 or later (LGPLv3+)
Classifier: Operating System :: OS Independent
Classifier: Programming Language :: Python :: 2.7
Classifier: Programming Language :: Python :: 3.3
Classifier: Programming Language :: Python :: 3.4
Classifier: Programming Language :: Python :: 3.5
Classifier: Programming Language :: Python :: 3.6
Classifier: Topic :: Desktop Environment
Classifier: Topic :: Utilities
Provides-Extra: all
Requires-Dist: sphinx (>=1.5); extra == 'all'
Requires-Dist: sphinx-rtd-theme; extra == 'all'
Provides-Extra: develop
Requires-Dist: sphinx (>=1.5); extra == 'develop'
Requires-Dist: sphinx-rtd-theme; extra == 'develop'
